vtds_provider_mock/__init__.py
vtds_provider_mock/private/__init__.py
vtds_provider_mock/private/api_objects.py
vtds_provider_mock/private/common.py
vtds_provider_mock/private/config.py
vtds_provider_mock/private/provider.py
vtds_provider_mock/private/secret_manager.py
vtds_provider_mock/private/config/README.md
vtds_provider_mock/private/config/config.yaml
vtds_provider_mock/private/config/test_overlay.yaml
vtds_provider_mock-0.0.5.dist-info/licenses/LICENSE
vtds_provider_mock-0.0.5.dist-info/METADATA
vtds_provider_mock-0.0.5.dist-info/WHEEL
vtds_provider_mock-0.0.5.dist-info/top_level.txt
vtds_provider_mock-0.0.5.dist-info/RECORD
