Metadata-Version: 2.4
Name: vtds_provider_mock
Version: 0.0.5
Summary: Mock Provider Layer Plugin for the Virtual Test Development System (vTDS) suite
Author-email: Eric Lund <eric.lund@hpe.com>
Maintainer-email: Eric Lund <eric.lund@hpe.com>
Classifier: License :: OSI Approved :: MIT License
Classifier: Natural Language :: English
Classifier: Operating System :: POSIX
Classifier: Programming Language :: Python :: 3 :: Only
Classifier: Programming Language :: Python :: 3.9
Classifier: Programming Language :: Python :: 3.10
Classifier: Programming Language :: Python :: 3.11
Classifier: Programming Language :: Python :: 3.12
Requires-Python: >=3.9
License-File: LICENSE
Requires-Dist: pyyaml~=6.0
Requires-Dist: vtds_base~=0.0
Provides-Extra: build
Requires-Dist: build~=1.3.0; extra == "build"
Provides-Extra: ci
Requires-Dist: nox~=2025.5.1; extra == "ci"
Provides-Extra: docs
Provides-Extra: style
Requires-Dist: pycodestyle~=2.11; extra == "style"
Provides-Extra: lint
Requires-Dist: pylint~=3.3; extra == "lint"
Provides-Extra: test
Requires-Dist: pytest~=8.4.1; extra == "test"
Requires-Dist: pytest-cov~=6.2; extra == "test"
Requires-Dist: coverage~=7.4; extra == "test"
Dynamic: license-file
